aa_theme_xix/__init__.py
aa_theme_xix/apps.py
aa_theme_xix/static/aa_theme_xix/css/dashboard-dark.css
aa_theme_xix/static/aa_theme_xix/css/dashboard-light.css
aa_theme_xix/static/aa_theme_xix/css/login-page.css
aa_theme_xix/static/aa_theme_xix/icons/android-chrome-192x192.png
aa_theme_xix/static/aa_theme_xix/icons/android-chrome-36x36.png
aa_theme_xix/static/aa_theme_xix/icons/android-chrome-48x48.png
aa_theme_xix/static/aa_theme_xix/icons/apple-touch-icon-57x57.png
aa_theme_xix/static/aa_theme_xix/icons/apple-touch-icon.png
aa_theme_xix/static/aa_theme_xix/icons/favicon-16x16.png
aa_theme_xix/static/aa_theme_xix/icons/favicon-32x32.png
aa_theme_xix/static/aa_theme_xix/icons/favicon.ico
aa_theme_xix/static/aa_theme_xix/img/.gitkeep
aa_theme_xix/static/aa_theme_xix/img/eve-sso-login-black-large.png
aa_theme_xix/static/aa_theme_xix/img/eve-sso-login-white-large.png
aa_theme_xix/templates/allianceauth/base.html
aa_theme_xix/templates/allianceauth/icons.html
aa_theme_xix/templates/allianceauth/side-menu.html
aa_theme_xix/templates/allianceauth/top-menu.html
aa_theme_xix/templates/mumbletemps/link.html
aa_theme_xix/templates/mumbletemps/login.html
aa_theme_xix/templates/public/base.html
aa_theme_xix/templates/public/middle_box.html
aa_theme_xix-0.2.1.dist-info/LICENSE
aa_theme_xix-0.2.1.dist-info/METADATA
aa_theme_xix-0.2.1.dist-info/WHEEL
aa_theme_xix-0.2.1.dist-info/RECORD
