Metadata-Version: 2.1
Name: aa-theme-xix
Version: 0.2.1
Summary: Theme for auth.legionofdeath.ru
Home-page: https://gitlab.com/legion-of-xxdeathxx/aa-theme-xix
License: GPL-3.0-or-later
Author: Boris Talovikov
Author-email: boris@talovikov.ru
Requires-Python: >=3.10
Classifier: License :: OSI Approved :: GNU General Public License v3 or later (GPLv3+)
Classifier: Programming Language :: Python :: 3
Classifier: Programming Language :: Python :: 3.10
Classifier: Programming Language :: Python :: 3.11
Requires-Dist: allianceauth (>=3.6)
Project-URL: Repository, https://gitlab.com/legion-of-xxdeathxx/aa-theme-xix
